CHANGES.rst
CONTRIBUTORS.rst
MANIFEST.in
README.rst
bootstrap.py
buildout.cfg
setup.py
cpskin/__init__.py
cpskin.diazotheme.dreamRightPortletBasic.egg-info/PKG-INFO
cpskin.diazotheme.dreamRightPortletBasic.egg-info/SOURCES.txt
cpskin.diazotheme.dreamRightPortletBasic.egg-info/dependency_links.txt
cpskin.diazotheme.dreamRightPortletBasic.egg-info/entry_points.txt
cpskin.diazotheme.dreamRightPortletBasic.egg-info/namespace_packages.txt
cpskin.diazotheme.dreamRightPortletBasic.egg-info/not-zip-safe
cpskin.diazotheme.dreamRightPortletBasic.egg-info/requires.txt
cpskin.diazotheme.dreamRightPortletBasic.egg-info/top_level.txt
cpskin/diazotheme/__init__.py
cpskin/diazotheme/dreamRightPortletBasic/__init__.py
cpskin/diazotheme/dreamRightPortletBasic/configure.zcml
cpskin/diazotheme/dreamRightPortletBasic/upgradehandlers.py
cpskin/diazotheme/dreamRightPortletBasic/profiles/default/cssregistry.xml
cpskin/diazotheme/dreamRightPortletBasic/profiles/default/jsregistry.xml
cpskin/diazotheme/dreamRightPortletBasic/profiles/default/lessregistry.xml
cpskin/diazotheme/dreamRightPortletBasic/profiles/default/metadata.xml
cpskin/diazotheme/dreamRightPortletBasic/profiles/default/theme.xml
cpskin/diazotheme/dreamRightPortletBasic/profiles/uninstall/cssregistry.xml
cpskin/diazotheme/dreamRightPortletBasic/profiles/uninstall/jsregistry.xml
cpskin/diazotheme/dreamRightPortletBasic/profiles/uninstall/lessregistry.xml
cpskin/diazotheme/dreamRightPortletBasic/static/manifest.cfg
cpskin/diazotheme/dreamRightPortletBasic/static/preview.png
cpskin/diazotheme/dreamRightPortletBasic/static/rules.xml
cpskin/diazotheme/dreamRightPortletBasic/static/css/styles.css
cpskin/diazotheme/dreamRightPortletBasic/static/fragments/give_a_day.pt
cpskin/diazotheme/dreamRightPortletBasic/static/fragments/search.pt
cpskin/diazotheme/dreamRightPortletBasic/static/less/styles.less
cpskin/diazotheme/dreamRightPortletBasic/static/less/variables.less
cpskin/diazotheme/dreamRightPortletBasic/static/rules/content.xml
docs/LICENSE.GPL
docs/LICENSE.rst